odoo/addons/web_widget_dropdown_dynamic/README.rst
odoo/addons/web_widget_dropdown_dynamic/__init__.py
odoo/addons/web_widget_dropdown_dynamic/__manifest__.py
odoo/addons/web_widget_dropdown_dynamic/i18n/es.po
odoo/addons/web_widget_dropdown_dynamic/i18n/sk_SK.po
odoo/addons/web_widget_dropdown_dynamic/i18n/web_widget_dropdown_dynamic.pot
odoo/addons/web_widget_dropdown_dynamic/readme/CONTRIBUTORS.rst
odoo/addons/web_widget_dropdown_dynamic/readme/DESCRIPTION.rst
odoo/addons/web_widget_dropdown_dynamic/readme/USAGE.rst
odoo/addons/web_widget_dropdown_dynamic/static/description/icon.png
odoo/addons/web_widget_dropdown_dynamic/static/description/index.html
odoo/addons/web_widget_dropdown_dynamic/static/src/js/basic_model.js
odoo/addons/web_widget_dropdown_dynamic/static/src/js/field_dynamic_dropdown.js
odoo/addons/web_widget_dropdown_dynamic/static/tests/web_widget_dropdown_dynamic_tests.js
odoo/addons/web_widget_dropdown_dynamic/templates/assets.xml
odoo13_addon_web_widget_dropdown_dynamic-13.0.1.0.1.dev11.dist-info/METADATA
odoo13_addon_web_widget_dropdown_dynamic-13.0.1.0.1.dev11.dist-info/WHEEL
odoo13_addon_web_widget_dropdown_dynamic-13.0.1.0.1.dev11.dist-info/top_level.txt
odoo13_addon_web_widget_dropdown_dynamic-13.0.1.0.1.dev11.dist-info/RECORD
